client.py
server.py
far_oracle-1.0.8.dist-info/licenses/LICENSE
far_oracle-1.0.8.dist-info/METADATA
far_oracle-1.0.8.dist-info/WHEEL
far_oracle-1.0.8.dist-info/entry_points.txt
far_oracle-1.0.8.dist-info/top_level.txt
far_oracle-1.0.8.dist-info/RECORD
