Metadata-Version: 2.4
Name: far-oracle
Version: 1.0.8
Summary: MCP Server for Federal Acquisition Regulations (FAR) search
Author: blueskylineassets
License: MIT
Project-URL: Homepage, https://github.com/blueskylineassets/far-mcp-server
Project-URL: Repository, https://github.com/blueskylineassets/far-mcp-server
Project-URL: RapidAPI, https://rapidapi.com/yschang/api/far-rag-federal-acquisition-regulation-search
Keywords: mcp,far,federal-acquisition-regulations,government-contracting,ai-agent
Classifier: Development Status :: 4 - Beta
Classifier: Intended Audience :: Developers
Classifier: License :: OSI Approved :: MIT License
Classifier: Programming Language :: Python :: 3
Classifier: Programming Language :: Python :: 3.10
Classifier: Programming Language :: Python :: 3.11
Classifier: Programming Language :: Python :: 3.12
Requires-Python: >=3.10
License-File: LICENSE
Requires-Dist: mcp>=1.0.0
Requires-Dist: httpx>=0.25.0
Requires-Dist: python-dotenv>=1.0.0
Dynamic: license-file
